CHANGES.rst
MANIFEST.in
README.rst
pyproject.toml
setup.cfg
setup.py
coaster/__init__.py
coaster/_version.py
coaster/app.py
coaster/assets.py
coaster/auth.py
coaster/db.py
coaster/docflow.py
coaster/gfm.py
coaster/logger.py
coaster/manage.py
coaster/nlp.py
coaster/signals.py
coaster.egg-info/PKG-INFO
coaster.egg-info/SOURCES.txt
coaster.egg-info/dependency_links.txt
coaster.egg-info/not-zip-safe
coaster.egg-info/requires.txt
coaster.egg-info/top_level.txt
coaster/sqlalchemy/__init__.py
coaster/sqlalchemy/annotations.py
coaster/sqlalchemy/columns.py
coaster/sqlalchemy/comparators.py
coaster/sqlalchemy/functions.py
coaster/sqlalchemy/immutable_annotation.py
coaster/sqlalchemy/markdown.py
coaster/sqlalchemy/mixins.py
coaster/sqlalchemy/registry.py
coaster/sqlalchemy/roles.py
coaster/sqlalchemy/statemanager.py
coaster/utils/__init__.py
coaster/utils/classes.py
coaster/utils/datetime.py
coaster/utils/markdown.py
coaster/utils/misc.py
coaster/utils/text.py
coaster/utils/tsquery.py
coaster/views/__init__.py
coaster/views/classview.py
coaster/views/decorators.py
coaster/views/misc.py
docs/Makefile
docs/app.rst
docs/assets.rst
docs/auth.rst
docs/conf.py
docs/conf.pyc
docs/db.rst
docs/docflow.rst
docs/index.rst
docs/logger.rst
docs/manage.rst
docs/nlp.rst
docs/__pycache__/conf.cpython-37.pyc
docs/__pycache__/conf.cpython-38.pyc
docs/sqlalchemy/annotations.rst
docs/sqlalchemy/columns.rst
docs/sqlalchemy/comparators.rst
docs/sqlalchemy/functions.rst
docs/sqlalchemy/immutable_annotation.rst
docs/sqlalchemy/index.rst
docs/sqlalchemy/mixins.rst
docs/sqlalchemy/registry.rst
docs/sqlalchemy/roles.rst
docs/sqlalchemy/statemanager.rst
docs/utils/classes.rst
docs/utils/datetime.rst
docs/utils/index.rst
docs/utils/markdown.rst
docs/utils/misc.rst
docs/utils/text.rst
docs/utils/tsquery.rst
docs/views/classview.rst
docs/views/decorators.rst
docs/views/index.rst
docs/views/misc.rst
tests/settings.py
tests/test_assets.py
tests/test_utils.py
tests/testing.py