Metadata-Version: 1.1
Name: coaster
Version: 0.6.1
Summary: Coaster for Flask
Home-page: https://github.com/hasgeek/coaster
Author: Kiran Jonnalagadda
Author-email: kiran@hasgeek.com
License: UNKNOWN
Keywords: coaster
Platform: UNKNOWN
Classifier: Programming Language :: Python
Classifier: Programming Language :: Python :: 2.7
Classifier: Programming Language :: Python :: 3.6
Classifier: Programming Language :: Python :: 3.7
Classifier: License :: OSI Approved :: BSD License
Classifier: Operating System :: OS Independent
Classifier: Intended Audience :: Developers
Classifier: Development Status :: 3 - Alpha
Classifier: Topic :: Software Development :: Libraries
